{"variants":{"":[{"model":"excavated_variants:block/dripstone_coal_ore_0"},{"model":"excavated_variants:block/dripstone_coal_ore_1"},{"model":"excavated_variants:block/dripstone_coal_ore_2"},{"model":"excavated_variants:block/dripstone_coal_ore_3"},{"model":"excavated_variants:block/dripstone_coal_ore_4"},{"model":"excavated_variants:block/dripstone_coal_ore_5"},{"model":"excavated_variants:block/dripstone_coal_ore_6"},{"model":"excavated_variants:block/dripstone_coal_ore_7"},{"model":"excavated_variants:block/dripstone_coal_ore_8"},{"model":"excavated_variants:block/dripstone_coal_ore_9"},{"model":"excavated_variants:block/dripstone_coal_ore_10"},{"model":"excavated_variants:block/dripstone_coal_ore_11"},{"model":"excavated_variants:block/dripstone_coal_ore_12"},{"model":"excavated_variants:block/dripstone_coal_ore_13"},{"model":"excavated_variants:block/dripstone_coal_ore_14"},{"model":"excavated_variants:block/dripstone_coal_ore_15"},{"model":"excavated_variants:block/dripstone_coal_ore_16"},{"model":"excavated_variants:block/dripstone_coal_ore_17"},{"model":"excavated_variants:block/dripstone_coal_ore_18"},{"model":"excavated_variants:block/dripstone_coal_ore_19"},{"model":"excavated_variants:block/dripstone_coal_ore_20"}]}}